explor.py
explor-0.1.21.dist-info/LICENSE
explor-0.1.21.dist-info/METADATA
explor-0.1.21.dist-info/WHEEL
explor-0.1.21.dist-info/top_level.txt
explor-0.1.21.dist-info/RECORD
